masksembles/__init__.py
masksembles/common.py
masksembles/exceptions.py
masksembles/keras.py
masksembles/torch.py
masksembles-1.1.1.dist-info/licenses/LICENSE
masksembles-1.1.1.dist-info/METADATA
masksembles-1.1.1.dist-info/WHEEL
masksembles-1.1.1.dist-info/top_level.txt
masksembles-1.1.1.dist-info/RECORD
