Metadata-Version: 2.4
Name: masksembles
Version: 1.1.1
Summary: Official implementation of Masksembles approach
Home-page: https://github.com/nikitadurasov/masksembles
Author: Nikita Durasov
Author-email: yassnda@gmail.com
License: MIT
Project-URL: Issues, https://github.com/nikitadurasov/masksembles/issues
Project-URL: Documentation, https://github.com/nikitadurasov/masksembles#readme
Keywords: uncertainty,ensembles,deep-learning,pytorch,tensorflow
Classifier: Programming Language :: Python :: 3
Classifier: License :: OSI Approved :: MIT License
Classifier: Operating System :: OS Independent
Requires-Python: >=3.8
License-File: LICENSE
Requires-Dist: numpy>=1.20
Provides-Extra: torch
Requires-Dist: torch>=1.12; extra == "torch"
Provides-Extra: tensorflow
Requires-Dist: tensorflow>=2.9; extra == "tensorflow"
Provides-Extra: dev
Requires-Dist: pytest; extra == "dev"
Requires-Dist: black; extra == "dev"
Requires-Dist: flake8; extra == "dev"
Dynamic: author
Dynamic: author-email
Dynamic: classifier
Dynamic: description
Dynamic: description-content-type
Dynamic: home-page
Dynamic: keywords
Dynamic: license
Dynamic: license-file
Dynamic: project-url
Dynamic: provides-extra
Dynamic: requires-dist
Dynamic: requires-python
Dynamic: summary
